pystopwords/__init__.py
pystopwords/core.py
pystopwords/gen_data.py
pystopwords/data/stopwords.zh.all.txt
pystopwords/data/stopwords.zh.baidu.txt
pystopwords/data/stopwords.zh.cn.txt
pystopwords/data/stopwords.zh.hit.txt
pystopwords/data/stopwords.zh.ict.txt
pystopwords/data/stopwords.zh.iso.txt
pystopwords/data/stopwords.zh.marimo.txt
pystopwords/data/stopwords.zh.scu.txt
pystopwords-0.0.2.dist-info/LICENSE
pystopwords-0.0.2.dist-info/METADATA
pystopwords-0.0.2.dist-info/WHEEL
pystopwords-0.0.2.dist-info/top_level.txt
pystopwords-0.0.2.dist-info/RECORD
