Metadata-Version: 2.1
Name: pystopwords
Version: 0.0.2
Summary: 中文停用词大全Python接口
License: MIT License
Keywords: 停用词 stopwords 中文 chinese
License-File: LICENSE
